xanespy/__init__.py
xanespy/beamlines.py
xanespy/edges.py
xanespy/exceptions.py
xanespy/fitting.py
xanespy/importers.py
xanespy/nanosurveyor.py
xanespy/plots.py
xanespy/qt_frame_view.py
xanespy/qt_frame_window.ui
xanespy/qt_frameset_presenter.py
xanespy/qt_map_view.py
xanespy/qt_map_window.ui
xanespy/sxstm.py
xanespy/txmstore.py
xanespy/utilities.py
xanespy/xanes_frameset.py
xanespy/xanes_math.py
xanespy/xanes_viewer.py
xanespy/xradia.py
xanespy-0.3.3.dist-info/DESCRIPTION.rst
xanespy-0.3.3.dist-info/METADATA
xanespy-0.3.3.dist-info/RECORD
xanespy-0.3.3.dist-info/WHEEL
xanespy-0.3.3.dist-info/entry_points.txt
xanespy-0.3.3.dist-info/metadata.json
xanespy-0.3.3.dist-info/top_level.txt
