Metadata-Version: 2.0
Name: xanespy
Version: 0.3.3
Summary: Tools for analyzing X-ray absorbance spectroscopy data
Home-page: https://github.com/canismarko/xanespy
Author: Mark Wolfman
Author-email: canismarko@gmail.com
License: UNKNOWN
Keywords: XANES X-ray microscopy operando
Platform: UNKNOWN
Classifier: Development Status :: 3 - Alpha
Classifier: Intended Audience :: Science/Research
Classifier: License :: OSI Approved :: GNU General Public License v3 or later (GPLv3+)
Classifier: Natural Language :: English
Classifier: Operating System :: POSIX :: Linux
Classifier: Programming Language :: Python :: 3.5
Classifier: Topic :: Scientific/Engineering :: Chemistry
Classifier: Topic :: Scientific/Engineering :: Physics
Classifier: Topic :: Scientific/Engineering :: Visualization
Requires-Dist: h5py
Requires-Dist: jinja2
Requires-Dist: matplotlib
Requires-Dist: numpy
Requires-Dist: olefile
Requires-Dist: pandas
Requires-Dist: pandas
Requires-Dist: pytz (>=2013b)
Requires-Dist: scikit-image
Requires-Dist: scikit-image
Requires-Dist: scikit-learn
Requires-Dist: tqdm
